README.rst
setup.py
spectrum/__init__.py
spectrum/conf.py
spectrum/filters.py
spectrum/django/__init__.py
spectrum/django/spectrum.py
spectrum/handlers/__init__.py
spectrum/handlers/base.py
spectrum/handlers/rest.py
spectrum/handlers/silent.py
spectrum/handlers/udp.py
spectrum/handlers/websocket.py
spectrum_python.egg-info/PKG-INFO
spectrum_python.egg-info/SOURCES.txt
spectrum_python.egg-info/dependency_links.txt
spectrum_python.egg-info/not-zip-safe
spectrum_python.egg-info/requires.txt
spectrum_python.egg-info/top_level.txt