Metadata-Version: 1.1
Name: spectrum-python
Version: 0.9.6
Summary: spectrum-python is a Python Logging Handler for Spectrum (devspectrum.com)
Home-page: https://github.com/SpectrumApp/spectrum-python/
Author: Frank Wiles
Author-email: frank@revsys.com
License: UNKNOWN
Platform: UNKNOWN
Classifier: Development Status :: 4 - Beta
Classifier: Intended Audience :: Developers
Classifier: License :: OSI Approved :: BSD License
Classifier: Operating System :: OS Independent
Classifier: Programming Language :: Python :: 2
Classifier: Programming Language :: Python :: 3
Classifier: Topic :: System :: Logging
